samosa-0.6.2.dist-info/METADATA
samosa-0.6.2.dist-info/WHEEL
samosa-0.6.2.dist-info/entry_points.txt
samosa-0.6.2.dist-info/licenses/COPYING
samosa/__init__.py
samosa/cli.py
samosa/git_task.py
samosa/resource/WORKFLOW.md
samosa/resource/__init__.py
samosa/resource/pre-commit
samosa-0.6.2.dist-info/RECORD
