Metadata-Version: 2.1
Name: samosa
Version: 0.6.2
Summary: Enforce a triangular Git workflow. If this is not possible, explain why.
Author-Email: David Seaward <david@librem.one>
License: AGPL-3.0-or-later
Project-URL: Source, https://gitlab.com/lfdo/toolchain/samosa
Project-URL: Project, https://lofidevops.neocities.org
Requires-Python: >=3.12
Requires-Dist: click>=8.1.6
Requires-Dist: pygit2>=1.18.0
Requires-Dist: sh>=2.0.5
